flask_replicated.py
flask_replicated-2.1.dist-info/METADATA
flask_replicated-2.1.dist-info/WHEEL
flask_replicated-2.1.dist-info/top_level.txt
flask_replicated-2.1.dist-info/RECORD
