Metadata-Version: 2.1
Name: flask-replicated
Version: 2.1
Summary: Flask SqlAlchemy router for stateful master-slave replication
Home-page: https://github.com/peterdemin/python-flask-replicated
Author: Peter Demin
Author-email: peterdemin@gmail.com
License: BSD
Keywords: flask sqlalchemy replication master slave
Platform: UNKNOWN
Classifier: Development Status :: 5 - Production/Stable
Classifier: Intended Audience :: Developers
Classifier: License :: OSI Approved :: BSD License
Classifier: Natural Language :: English
Classifier: Programming Language :: Python :: 2
Classifier: Programming Language :: Python :: 2.6
Classifier: Programming Language :: Python :: 2.7
Classifier: Programming Language :: Python :: 3
Classifier: Programming Language :: Python :: 3.5
Classifier: Programming Language :: Python :: 3.6
Classifier: Programming Language :: Python :: 3.7
